[
    {
        "Id": "1",
        "Desc": "通过本关",
        "ParamCnt": "0"
    },
    {
        "Id": "2",
        "Desc": "通关用时少于{0}秒",
        "ParamCnt": "1"
    },
    {
        "Id": "3",
        "Desc": "死亡次数少于{0}次",
        "ParamCnt": "1"
    },
    {
        "Id": "4",
        "Desc": "得分超过{0}",
        "ParamCnt": "1"
    },
    {
        "Id": "5",
        "Desc": "拾取了所有钻石",
        "ParamCnt": "0"
    },
    {
        "Id": "6",
        "Desc": "消灭了所有怪物",
        "ParamCnt": "0"
    },
    {
        "Id": "7",
        "Desc": "行走距离小于{0}米",
        "ParamCnt": "1"
    },
    {
        "Id": "8",
        "Desc": "跳跃次数小于{0}次",
        "ParamCnt": "1"
    },
    {
        "Id": "9",
        "Desc": "消灭的怪物少于{0}个",
        "ParamCnt": "1"
    },
    {
        "Id": "10",
        "Desc": "触发开关少于{0}次",
        "ParamCnt": "1"
    },
    {
        "Id": "11",
        "Desc": "不使用传送门",
        "ParamCnt": "0"
    },
    {
        "Id": "12",
        "Desc": "用激光消灭{0}个怪物",
        "ParamCnt": "1"
    },
    {
        "Id": "13",
        "Desc": "使怪物坠亡{0}次",
        "ParamCnt": "1"
    }
]