{"skeleton":{"hash":"QWGqA21wwYzB/ZhbQjM1GLWp/FQ","spine":"3.2.00","width":168,"height":154},"bones":[{"name":"root"},{"name":"bone","parent":"root"},{"name":"suo","parent":"bone","x":-14.53,"y":63.45},{"name":"yaoshi","parent":"bone","x":-23.95,"y":53.39}],"slots":[{"name":"images/yaoshi/yaoshi_suo_01","bone":"suo","attachment":"images/yaoshi/yaoshi_suo_01"},{"name":"images/yaoshi/yaoshi_01","bone":"yaoshi"}],"skins":{"default":{"images/yaoshi/yaoshi_01":{"images/yaoshi/yaoshi_01":{"width":98,"height":89},"images/yaoshi/yaoshi_02":{"width":98,"height":89},"images/yaoshi/yaoshi_03":{"width":98,"height":89},"images/yaoshi/yaoshi_04":{"width":98,"height":89}},"images/yaoshi/yaoshi_suo_01":{"images/yaoshi/yaoshi_suo_01":{"x":14.53,"y":14.53,"width":168,"height":154},"images/yaoshi/yaoshi_suo_02":{"x":14.53,"y":14.53,"width":168,"height":154},"images/yaoshi/yaoshi_suo_03":{"x":14.53,"y":14.53,"width":168,"height":154},"images/yaoshi/yaoshi_suo_04":{"x":14.53,"y":14.53,"width":168,"height":154}}}},"animations":{"Open":{"slots":{"images/yaoshi/yaoshi_01":{"color":[{"time":0.7333,"color":"fffffffb"},{"time":0.9333,"color":"ffffffff"},{"time":1.0666,"color":"ffffff00"}],"attachment":[{"time":0.1333,"name":"images/yaoshi/yaoshi_02"},{"time":0.2,"name":"images/yaoshi/yaoshi_02"},{"time":0.3333,"name":"images/yaoshi/yaoshi_03"},{"time":0.5333,"name":"images/yaoshi/yaoshi_04"},{"time":0.6,"name":"images/yaoshi/yaoshi_04"},{"time":0.7333,"name":"images/yaoshi/yaoshi_01"},{"time":1.1333,"name":null},{"time":1.3,"name":null}]},"images/yaoshi/yaoshi_suo_01":{"attachment":[{"time":1,"name":"images/yaoshi/yaoshi_suo_02"},{"time":1.1333,"name":"images/yaoshi/yaoshi_suo_03"},{"time":1.2666,"name":"images/yaoshi/yaoshi_suo_04"},{"time":1.6333,"name":"images/yaoshi/yaoshi_suo_04"}]}},"bones":{"yaoshi":{"rotate":[{"time":0,"angle":0,"curve":"stepped"},{"time":0.1333,"angle":0},{"time":0.1666,"angle":2},{"time":0.2,"angle":0,"curve":"stepped"},{"time":0.3333,"angle":0},{"time":0.3666,"angle":358},{"time":0.4,"angle":0,"curve":"stepped"},{"time":0.5333,"angle":0},{"time":0.5666,"angle":4.18},{"time":0.6,"angle":0}],"translate":[{"time":0,"x":0,"y":0}],"scale":[{"time":0,"x":1,"y":1}]},"suo":{"rotate":[{"time":0,"angle":0},{"time":0.0333,"angle":5.28},{"time":0.0666,"angle":-1.93},{"time":0.1,"angle":0},{"time":0.1333,"angle":5.28},{"time":0.1666,"angle":-1.93},{"time":0.2333,"angle":0,"curve":"stepped"},{"time":0.9,"angle":0},{"time":0.9333,"angle":2},{"time":0.9666,"angle":0}],"translate":[{"time":0,"x":0,"y":0},{"time":0.0333,"x":0,"y":-2.56},{"time":0.0666,"x":0,"y":1.28},{"time":0.1,"x":0,"y":0},{"time":0.1333,"x":0,"y":-2.56},{"time":0.1666,"x":0,"y":1.28},{"time":0.2333,"x":0,"y":0,"curve":"stepped"},{"time":0.9,"x":0,"y":0},{"time":0.9333,"x":0,"y":-2.56},{"time":0.9666,"x":0,"y":0}],"scale":[{"time":0,"x":1,"y":1,"curve":"stepped"},{"time":0.2,"x":1,"y":1,"curve":"stepped"},{"time":0.3,"x":1,"y":1,"curve":"stepped"},{"time":0.4333,"x":1,"y":1,"curve":"stepped"},{"time":0.9,"x":1,"y":1,"curve":"stepped"},{"time":0.9666,"x":1,"y":1}]}}}}}