{"skeleton":{"hash":"hq2qPBxmgl+HbjKGacqN5zUR6/E","spine":"3.2.00","width":147.37,"height":153.66},"bones":[{"name":"huangji","scaleX":0.8,"scaleY":0.8},{"name":"huangji/shenti","parent":"huangji","y":18.31},{"name":"ban","parent":"huangji/shenti","x":-0.52,"y":-0.48},{"name":"shenti","parent":"ban","length":143.72,"x":-0.11,"y":10.94,"rotation":89.49},{"name":"bone2","parent":"shenti","length":29.21,"x":52.91,"y":-56.24,"rotation":131.73},{"name":"bone3","parent":"shenti","length":30.88,"x":51.14,"y":56.38,"rotation":-123.43},{"name":"bone4","parent":"shenti","x":75.18,"y":-1.4,"rotation":-89.49},{"name":"houlun","parent":"ban","x":31.22,"y":0.03},{"name":"qianlun","parent":"ban","x":-30.39,"y":0.03}],"slots":[{"name":"huangji/zhengchang","bone":"shenti","attachment":"images/huangji/zhengchang"},{"name":"images/huangji/ban","bone":"ban","attachment":"images/huangji/ban"},{"name":"huangji/qiankun","bone":"qianlun","attachment":"images/huangji/qianlun"},{"name":"images/huangji/hpulun","bone":"houlun","attachment":"images/huangji/hpulun"},{"name":"huangji/yanjing","bone":"bone4","attachment":"./images/huangji/yanjing"},{"name":"huangji/youshou","bone":"bone3","attachment":"./images/huangji/youshou"},{"name":"huangji/zuoshou","bone":"bone2","attachment":"./images/huangji/zuoshou"}],"skins":{"default":{"huangji/qiankun":{"images/huangji/qianlun":{"x":0.75,"y":0.86,"width":39,"height":39}},"huangji/yanjing":{"./images/huangji/yanjing":{"x":-0.85,"y":-4.31,"rotation":-0.38,"width":77,"height":14}},"huangji/youshou":{"./images/huangji/youshou":{"x":25.52,"y":3.07,"rotation":33.69,"width":57,"height":38}},"huangji/zhengchang":{"images/huangji/shangjiya":{"x":58.82,"y":-0.38,"rotation":-89.74,"width":180,"height":156},"images/huangji/shangtan":{"x":80.14,"y":-0.29,"rotation":-89.74,"width":180,"height":198},"images/huangji/youjiya":{"x":70.18,"y":8.7,"rotation":-89.74,"width":163,"height":178},"images/huangji/youtan":{"x":69.82,"y":-8.77,"rotation":-89.74,"width":197,"height":178},"images/huangji/zhengchang":{"type":"mesh","uvs":[0.84298,0.06914,0.91754,0.16832,1,0.41031,0.99999,0.56899,0.99999,0.87841,0.94505,0.97222,0.83906,0.99999,0.10921,1,0.01961,0.93256,0,0.69197,0,0.42221,0.02746,0.26749,0.08959,0.14055,0.17984,0.06517,0.39958,0,0.67818,0,0.30541,0.93395,0.47021,0.92999,0.70172,0.92999,0.21123,0.7475,0.5016,0.80304,0.81551,0.72767,0.79197,0.3984,0.5016,0.21592,0.23085,0.39047,0.50553,0.43014,0.50553,0.6761],"triangles":[23,14,15,23,24,13,23,13,14,12,13,24,11,12,24,0,23,15,22,0,1,22,23,0,22,1,2,10,11,24,25,23,22,24,23,25,3,22,2,26,25,22,24,25,26,9,10,24,19,9,24,21,22,3,26,22,21,26,19,24,20,19,26,20,26,21,4,21,3,18,20,21,21,6,18,20,16,19,17,20,18,8,9,19,17,16,20,7,8,19,4,5,21,5,6,21,16,7,19,7,16,17,6,7,17,6,17,18],"vertices":[150.15,-63.08,132.16,-76.87999,88.18,-92.24,59.3,-92.37,2.99,-92.62,-14.12,-82.58999,-19.26,-63.11,-19.85,71.17,-7.65,87.71,36.11,91.52,85.2,91.73,113.38,86.81,136.54,75.48,150.33,58.93,162.37,18.54999,162.6,-32.7,-7.67,35.13,-6.82,4.81,-6.63,-37.78,26.17,52.61,16.29999,-0.86,30.27,-58.55,90.18,-53.96,123.16,-0.38,91.17,49.28,84.17,-1.28,39.41,-1.48],"hull":16},"images/huangji/zuojiya":{"x":70.64,"y":-8.6,"rotation":-89.74,"width":164,"height":176},"images/huangji/zuotan":{"x":70.08,"y":8.67,"rotation":-89.74,"width":198,"height":178}},"huangji/zuoshou":{"./images/huangji/zuoshou":{"x":24.5,"y":-4.94,"rotation":138.52,"width":54,"height":38}},"images/huangji/ban":{"images/huangji/ban":{"x":0.52,"y":0.48,"width":108,"height":21}},"images/huangji/hpulun":{"images/huangji/hpulun":{"x":0.4,"y":0.86,"width":38,"height":39}}}},"animations":{"Idle":{"bones":{"huangji":{"rotate":[{"time":0,"angle":0,"curve":"stepped"},{"time":0.8,"angle":0}],"translate":[{"time":0,"x":0,"y":0,"curve":"stepped"},{"time":0.8,"x":0,"y":0}],"scale":[{"time":0,"x":1,"y":1,"curve":"stepped"},{"time":0.8,"x":1,"y":1}]},"huangji/shenti":{"rotate":[{"time":0,"angle":0,"curve":"stepped"},{"time":0.8,"angle":0}],"translate":[{"time":0,"x":0,"y":0,"curve":"stepped"},{"time":0.8,"x":0,"y":0}],"scale":[{"time":0,"x":1,"y":1,"curve":"stepped"},{"time":0.8,"x":1,"y":1}]},"ban":{"rotate":[{"time":0,"angle":0,"curve":"stepped"},{"time":0.8,"angle":0}],"translate":[{"time":0,"x":0,"y":0},{"time":0.2,"x":0,"y":-0.92},{"time":0.4,"x":0,"y":0},{"time":0.6,"x":0,"y":-0.92},{"time":0.8,"x":0,"y":0}],"scale":[{"time":0,"x":1,"y":1,"curve":"stepped"},{"time":0.8,"x":1,"y":1}]},"qianlun":{"rotate":[{"time":0,"angle":0,"curve":"stepped"},{"time":0.8,"angle":0}],"translate":[{"time":0,"x":0,"y":0},{"time":0.2,"x":0,"y":0.69},{"time":0.4,"x":0,"y":-0.24},{"time":0.6,"x":0,"y":0.56},{"time":0.8,"x":0,"y":0}],"scale":[{"time":0,"x":1,"y":1,"curve":"stepped"},{"time":0.8,"x":1,"y":1}]},"houlun":{"rotate":[{"time":0,"angle":0,"curve":"stepped"},{"time":0.8,"angle":0}],"translate":[{"time":0,"x":0,"y":0},{"time":0.2,"x":0,"y":0.69},{"time":0.4,"x":0,"y":0.13},{"time":0.6,"x":0,"y":0.71},{"time":0.8,"x":0,"y":0}],"scale":[{"time":0,"x":1,"y":1,"curve":"stepped"},{"time":0.8,"x":1,"y":1}]},"shenti":{"rotate":[{"time":0,"angle":0},{"time":0.2,"angle":-0.32},{"time":0.4,"angle":-0.08},{"time":0.6,"angle":0.25},{"time":0.8,"angle":0}],"translate":[{"time":0,"x":0,"y":0,"curve":"stepped"},{"time":0.8,"x":0,"y":0}],"scale":[{"time":0,"x":1,"y":1},{"time":0.4,"x":1.019,"y":1},{"time":0.8,"x":1,"y":1}]},"bone2":{"rotate":[{"time":0,"angle":0},{"time":0.4,"angle":-6.35},{"time":0.8,"angle":0}],"translate":[{"time":0,"x":0,"y":0},{"time":0.4,"x":3.31,"y":0.03},{"time":0.8,"x":0,"y":0}],"scale":[{"time":0,"x":1,"y":1,"curve":"stepped"},{"time":0.8,"x":1,"y":1}]},"bone3":{"rotate":[{"time":0,"angle":0},{"time":0.4,"angle":8.06},{"time":0.8,"angle":0}],"translate":[{"time":0,"x":0,"y":0},{"time":0.4,"x":1.85,"y":0.01},{"time":0.8,"x":0,"y":0}],"scale":[{"time":0,"x":1,"y":1,"curve":"stepped"},{"time":0.8,"x":1,"y":1}]},"bone4":{"rotate":[{"time":0,"angle":0,"curve":"stepped"},{"time":0.4,"angle":0,"curve":"stepped"},{"time":0.8,"angle":0}],"translate":[{"time":0,"x":6.42,"y":-0.49},{"time":0.4,"x":9.36,"y":-1.07},{"time":0.8,"x":6.42,"y":-0.49}],"scale":[{"time":0,"x":1.1,"y":1.1},{"time":0.4,"x":1.15,"y":0.95},{"time":0.8,"x":1.1,"y":1.1}]}},"ffd":{"default":{"huangji/zhengchang":{"images/huangji/zhengchang":[{"time":0,"offset":46,"vertices":[-0.87997]},{"time":0.4,"offset":38,"vertices":[6.32717,1.89775,3.81583,0.03334,6.35394,-1.16473,3.82653,-1.19166,4.17836,0.03651,3.79977,1.87083,6.34324,0.06027,6.34324,0.06027]},{"time":0.8,"offset":46,"vertices":[-0.87997]}]}}}},"Left":{"slots":{"huangji/zhengchang":{"attachment":[{"time":0,"name":"images/huangji/zhengchang"},{"time":0.0666,"name":"images/huangji/zuojiya"},{"time":0.1333,"name":"images/huangji/zuotan"},{"time":0.2333,"name":"images/huangji/zhengchang"}]}},"bones":{"huangji":{"rotate":[{"time":0,"angle":0,"curve":"stepped"},{"time":0.2333,"angle":0}],"translate":[{"time":0,"x":0,"y":0,"curve":"stepped"},{"time":0.2333,"x":0,"y":0}],"scale":[{"time":0,"x":1,"y":1,"curve":"stepped"},{"time":0.2333,"x":1,"y":1}]},"huangji/shenti":{"rotate":[{"time":0,"angle":0,"curve":"stepped"},{"time":0.2333,"angle":0}],"translate":[{"time":0,"x":0,"y":0,"curve":"stepped"},{"time":0.2333,"x":0,"y":0}],"scale":[{"time":0,"x":1,"y":1,"curve":"stepped"},{"time":0.2333,"x":1,"y":1}]},"ban":{"rotate":[{"time":0,"angle":0,"curve":"stepped"},{"time":0.2333,"angle":0}],"translate":[{"time":0,"x":0,"y":0},{"time":0.0666,"x":0,"y":-1.93,"curve":"stepped"},{"time":0.1,"x":0,"y":-1.93},{"time":0.1333,"x":0,"y":1.6},{"time":0.2333,"x":0,"y":0}],"scale":[{"time":0,"x":1,"y":1,"curve":"stepped"},{"time":0.2333,"x":1,"y":1}]},"qianlun":{"rotate":[{"time":0,"angle":0,"curve":"stepped"},{"time":0.2333,"angle":0}],"translate":[{"time":0,"x":0,"y":0},{"time":0.0666,"x":0,"y":1.45},{"time":0.1,"x":0,"y":1.54},{"time":0.1333,"x":0,"y":-2.09},{"time":0.2333,"x":0,"y":0}],"scale":[{"time":0,"x":1,"y":1,"curve":"stepped"},{"time":0.2333,"x":1,"y":1}]},"houlun":{"rotate":[{"time":0,"angle":0,"curve":"stepped"},{"time":0.2333,"angle":0}],"translate":[{"time":0,"x":0,"y":0},{"time":0.0666,"x":0,"y":1.45},{"time":0.1,"x":0,"y":1.54},{"time":0.1333,"x":0,"y":-2.09},{"time":0.2333,"x":0,"y":0}],"scale":[{"time":0,"x":1,"y":1,"curve":"stepped"},{"time":0.2333,"x":1,"y":1}]},"shenti":{"rotate":[{"time":0,"angle":0,"curve":"stepped"},{"time":0.2333,"angle":0}],"scale":[{"time":0.0666,"x":1.008,"y":1},{"time":0.1,"x":0.963,"y":0.984},{"time":0.1333,"x":1.025,"y":1.073},{"time":0.2333,"x":0.997,"y":1}]},"bone2":{"rotate":[{"time":0,"angle":0},{"time":0.0666,"angle":-6.39},{"time":0.1333,"angle":14.84},{"time":0.2333,"angle":0}],"translate":[{"time":0,"x":0,"y":0},{"time":0.0666,"x":-1.78,"y":-0.01},{"time":0.1,"x":-0.29,"y":0},{"time":0.1333,"x":0.37,"y":0},{"time":0.2333,"x":0,"y":0}],"scale":[{"time":0,"x":1,"y":1,"curve":"stepped"},{"time":0.2333,"x":1,"y":1}]},"bone3":{"rotate":[{"time":0,"angle":0},{"time":0.0666,"angle":4.44},{"time":0.1333,"angle":-16.16},{"time":0.2333,"angle":0}],"translate":[{"time":0,"x":0,"y":0},{"time":0.0333,"x":-1.19,"y":-0.01},{"time":0.0666,"x":-9.33,"y":-10.91},{"time":0.1,"x":-6.17,"y":-12.3},{"time":0.1333,"x":0.37,"y":0},{"time":0.2333,"x":0,"y":0}],"scale":[{"time":0,"x":1,"y":1,"curve":"stepped"},{"time":0.2333,"x":1,"y":1}]},"bone4":{"rotate":[{"time":0,"angle":0,"curve":"stepped"},{"time":0.2333,"angle":0}],"translate":[{"time":0,"x":0,"y":0,"curve":"stepped"},{"time":0.0333,"x":0,"y":0},{"time":0.0666,"x":0.02,"y":-2.71,"curve":"stepped"},{"time":0.1,"x":0.02,"y":-2.71},{"time":0.1333,"x":-0.02,"y":2.38},{"time":0.2333,"x":0,"y":0}],"scale":[{"time":0,"x":1,"y":1,"curve":"stepped"},{"time":0.2333,"x":1,"y":1}]}}},"Right":{"slots":{"huangji/zhengchang":{"attachment":[{"time":0,"name":"images/huangji/zhengchang"},{"time":0.0666,"name":"images/huangji/youjiya"},{"time":0.1333,"name":"images/huangji/youtan"},{"time":0.2333,"name":"images/huangji/zhengchang"}]}},"bones":{"huangji":{"rotate":[{"time":0,"angle":0,"curve":"stepped"},{"time":0.2333,"angle":0}],"translate":[{"time":0,"x":0,"y":0,"curve":"stepped"},{"time":0.2333,"x":0,"y":0}],"scale":[{"time":0,"x":1,"y":1,"curve":"stepped"},{"time":0.2333,"x":1,"y":1}]},"huangji/shenti":{"rotate":[{"time":0,"angle":0,"curve":"stepped"},{"time":0.2333,"angle":0}],"translate":[{"time":0,"x":0,"y":0,"curve":"stepped"},{"time":0.2333,"x":0,"y":0}],"scale":[{"time":0,"x":1,"y":1,"curve":"stepped"},{"time":0.2333,"x":1,"y":1}]},"ban":{"rotate":[{"time":0,"angle":0,"curve":"stepped"},{"time":0.2333,"angle":0}],"translate":[{"time":0,"x":0,"y":0},{"time":0.0666,"x":0,"y":-1.93,"curve":"stepped"},{"time":0.1,"x":0,"y":-1.93},{"time":0.1333,"x":0,"y":1.6},{"time":0.2333,"x":0,"y":0}],"scale":[{"time":0,"x":1,"y":1,"curve":"stepped"},{"time":0.2333,"x":1,"y":1}]},"qianlun":{"rotate":[{"time":0,"angle":0,"curve":"stepped"},{"time":0.2333,"angle":0}],"translate":[{"time":0,"x":0,"y":0},{"time":0.0666,"x":0,"y":1.45},{"time":0.1,"x":0,"y":1.54},{"time":0.1333,"x":0,"y":-2.09},{"time":0.2333,"x":0,"y":0}],"scale":[{"time":0,"x":1,"y":1,"curve":"stepped"},{"time":0.2333,"x":1,"y":1}]},"houlun":{"rotate":[{"time":0,"angle":0,"curve":"stepped"},{"time":0.2333,"angle":0}],"translate":[{"time":0,"x":0,"y":0},{"time":0.0666,"x":0,"y":1.45},{"time":0.1,"x":0,"y":1.54},{"time":0.1333,"x":0,"y":-2.09},{"time":0.2333,"x":0,"y":0}],"scale":[{"time":0,"x":1,"y":1,"curve":"stepped"},{"time":0.2333,"x":1,"y":1}]},"shenti":{"rotate":[{"time":0,"angle":0,"curve":"stepped"},{"time":0.2333,"angle":0}],"scale":[{"time":0.0666,"x":1.008,"y":1},{"time":0.1,"x":0.963,"y":0.984},{"time":0.1333,"x":1.025,"y":1.073},{"time":0.2333,"x":0.997,"y":1}]},"bone2":{"rotate":[{"time":0,"angle":0},{"time":0.0666,"angle":-6.39},{"time":0.1333,"angle":14.84},{"time":0.2333,"angle":0}],"translate":[{"time":0,"x":0,"y":0},{"time":0.0333,"x":-1.19,"y":-0.01},{"time":0.0666,"x":-9.03,"y":7.81},{"time":0.1,"x":-5.94,"y":11.25},{"time":0.1333,"x":0.67,"y":-3.67},{"time":0.2333,"x":0,"y":0}],"scale":[{"time":0,"x":1,"y":1,"curve":"stepped"},{"time":0.2333,"x":1,"y":1}]},"bone3":{"rotate":[{"time":0,"angle":0},{"time":0.0666,"angle":4.44},{"time":0.1333,"angle":-16.16},{"time":0.2333,"angle":0}],"translate":[{"time":0,"x":0,"y":0,"curve":"stepped"},{"time":0.2333,"x":0,"y":0}],"scale":[{"time":0,"x":1,"y":1,"curve":"stepped"},{"time":0.2333,"x":1,"y":1}]},"bone4":{"rotate":[{"time":0,"angle":0,"curve":"stepped"},{"time":0.2333,"angle":0}],"translate":[{"time":0,"x":0,"y":0,"curve":"stepped"},{"time":0.0333,"x":0,"y":0},{"time":0.0666,"x":-0.02,"y":2.78,"curve":"stepped"},{"time":0.1,"x":-0.02,"y":2.78},{"time":0.1333,"x":-1.03,"y":-3.76},{"time":0.2333,"x":0,"y":0}],"scale":[{"time":0,"x":1,"y":1,"curve":"stepped"},{"time":0.2333,"x":1,"y":1}]}}},"Run":{"bones":{"qianlun":{"rotate":[{"time":0,"angle":0},{"time":0.2333,"angle":64.41},{"time":0.4666,"angle":117.08},{"time":0.7,"angle":177.43},{"time":0.9333,"angle":-117.59},{"time":1.1666,"angle":-61.91},{"time":1.3666,"angle":-4.79}]},"houlun":{"rotate":[{"time":0,"angle":0},{"time":0.2333,"angle":68.81},{"time":0.4666,"angle":123.78},{"time":0.7,"angle":179},{"time":0.9333,"angle":-114.73},{"time":1.1666,"angle":-46.35},{"time":1.3666,"angle":-4.69}]},"ban":{"translate":[{"time":0,"x":0,"y":0},{"time":0.1,"x":0,"y":-0.92},{"time":0.2333,"x":0,"y":1.23},{"time":0.4,"x":0,"y":-1.84},{"time":0.5333,"x":0,"y":-1.58},{"time":0.7,"x":0,"y":1.54},{"time":0.8,"x":0,"y":0},{"time":0.9333,"x":0,"y":0.83},{"time":1.0666,"x":0,"y":0},{"time":1.1666,"x":0,"y":1.23},{"time":1.3,"x":0,"y":-0.61},{"time":1.3666,"x":0,"y":0}]},"shenti":{"scale":[{"time":0,"x":1,"y":1},{"time":0.2333,"x":1.016,"y":1},{"time":0.4333,"x":0.99,"y":1},{"time":0.7,"x":1.033,"y":1},{"time":0.8333,"x":0.989,"y":1},{"time":1.1666,"x":1.023,"y":1},{"time":1.3666,"x":0.997,"y":1}]},"bone4":{"rotate":[{"time":0,"angle":0,"curve":"stepped"},{"time":1.3666,"angle":0}],"translate":[{"time":0,"x":-4.96,"y":-0.04},{"time":0.3,"x":6.96,"y":0.06},{"time":0.4,"x":-5.02,"y":-0.04},{"time":0.7333,"x":6.25,"y":0.05},{"time":0.8666,"x":-6.26,"y":-0.05},{"time":1.2,"x":8.93,"y":0.07},{"time":1.3666,"x":-4.96,"y":-0.04}]},"bone3":{"rotate":[{"time":0,"angle":0},{"time":0.2333,"angle":3.99},{"time":0.4666,"angle":-4.28},{"time":0.7,"angle":2.53},{"time":0.9333,"angle":-2.73},{"time":1.1666,"angle":2.51},{"time":1.3666,"angle":0}],"translate":[{"time":0,"x":0,"y":0},{"time":0.2333,"x":3.35,"y":0.02},{"time":0.4666,"x":1.11,"y":0},{"time":0.7,"x":3.35,"y":0.02},{"time":0.8333,"x":-2.23,"y":-0.01},{"time":0.9333,"x":-0.55,"y":0},{"time":1.1,"x":2.79,"y":0.02},{"time":1.1666,"x":5.03,"y":0.04},{"time":1.3666,"x":0,"y":0}]},"bone2":{"rotate":[{"time":0,"angle":0},{"time":0.2333,"angle":3.99},{"time":0.4666,"angle":-4.28},{"time":0.7,"angle":2.53},{"time":0.9333,"angle":-2.73},{"time":1.1666,"angle":2.51},{"time":1.3666,"angle":0}],"translate":[{"time":0,"x":0,"y":0},{"time":0.2333,"x":3.35,"y":0.02},{"time":0.4666,"x":1.11,"y":0},{"time":0.7,"x":3.35,"y":0.02},{"time":0.8333,"x":-2.23,"y":-0.01},{"time":0.9333,"x":-0.55,"y":0},{"time":1.1,"x":2.79,"y":0.02},{"time":1.1666,"x":5.03,"y":0.04},{"time":1.3666,"x":0,"y":0}]}},"ffd":{"default":{"huangji/zhengchang":{"images/huangji/zhengchang":[{"time":0,"offset":52,"vertices":[1.00477]},{"time":0.2666,"offset":38,"vertices":[5.72447,0.05002,5.72447,0.05002,5.72447,0.05002,5.72447,0.05002,0,0,5.72447,0.05002,5.72447,0.05002,6.72925,0.0588]},{"time":0.3666,"offset":38,"vertices":[0.68425,0.00598,0.68425,0.00598,0.68425,0.00598,0.68425,0.00598,0,0,0.68425,0.00598,0.68425,0.00598,1.68903,0.01476]},{"time":0.7,"offset":38,"vertices":[4.07203,0.03558,4.07203,0.03558,4.07203,0.03558,4.07203,0.03558,0,0,4.07203,0.03558,4.07203,0.03558,5.07681,0.04436]},{"time":0.8333,"offset":38,"vertices":[-2.16615,-0.01892,-2.16615,-0.01892,-2.16615,-0.01892,-2.16615,-0.01892,0,0,-2.16615,-0.01892,-2.16615,-0.01892,-1.16137,-0.01014]},{"time":1.1666,"offset":38,"vertices":[5.96742,0.05214,5.96742,0.05214,5.96742,0.05214,5.96742,0.05214,0,0,5.96742,0.05214,5.96742,0.05214,6.9722,0.06092]},{"time":1.3666,"offset":52,"vertices":[1.00477]}]}}}},"Up":{"slots":{"huangji/zhengchang":{"attachment":[{"time":0,"name":"images/huangji/zhengchang"},{"time":0.0666,"name":"images/huangji/shangjiya"},{"time":0.1333,"name":"images/huangji/shangtan"},{"time":0.2333,"name":"images/huangji/zhengchang"}]}},"bones":{"huangji":{"rotate":[{"time":0,"angle":0,"curve":"stepped"},{"time":0.2333,"angle":0}],"translate":[{"time":0,"x":0,"y":0,"curve":"stepped"},{"time":0.2333,"x":0,"y":0}],"scale":[{"time":0,"x":1,"y":1,"curve":"stepped"},{"time":0.2333,"x":1,"y":1}]},"huangji/shenti":{"rotate":[{"time":0,"angle":0,"curve":"stepped"},{"time":0.2333,"angle":0}],"translate":[{"time":0,"x":0,"y":0,"curve":"stepped"},{"time":0.2333,"x":0,"y":0}],"scale":[{"time":0,"x":1,"y":1,"curve":"stepped"},{"time":0.2333,"x":1,"y":1}]},"ban":{"rotate":[{"time":0,"angle":0,"curve":"stepped"},{"time":0.2333,"angle":0}],"translate":[{"time":0,"x":0,"y":0},{"time":0.0666,"x":0,"y":-1.93,"curve":"stepped"},{"time":0.1,"x":0,"y":-1.93},{"time":0.1333,"x":0,"y":1.6},{"time":0.2333,"x":0,"y":0}],"scale":[{"time":0,"x":1,"y":1,"curve":"stepped"},{"time":0.2333,"x":1,"y":1}]},"qianlun":{"rotate":[{"time":0,"angle":0,"curve":"stepped"},{"time":0.2333,"angle":0}],"translate":[{"time":0,"x":0,"y":0},{"time":0.0666,"x":0,"y":1.45},{"time":0.1,"x":0,"y":1.54},{"time":0.1333,"x":0,"y":-2.09},{"time":0.2333,"x":0,"y":0}],"scale":[{"time":0,"x":1,"y":1,"curve":"stepped"},{"time":0.2333,"x":1,"y":1}]},"houlun":{"rotate":[{"time":0,"angle":0,"curve":"stepped"},{"time":0.2333,"angle":0}],"translate":[{"time":0,"x":0,"y":0},{"time":0.0666,"x":0,"y":1.45},{"time":0.1,"x":0,"y":1.54},{"time":0.1333,"x":0,"y":-2.09},{"time":0.2333,"x":0,"y":0}],"scale":[{"time":0,"x":1,"y":1,"curve":"stepped"},{"time":0.2333,"x":1,"y":1}]},"shenti":{"rotate":[{"time":0,"angle":0,"curve":"stepped"},{"time":0.2333,"angle":0}],"scale":[{"time":0.0666,"x":1.008,"y":1},{"time":0.1,"x":0.941,"y":1},{"time":0.1333,"x":1.085,"y":1},{"time":0.2333,"x":0.997,"y":1}]},"bone2":{"rotate":[{"time":0,"angle":0},{"time":0.0666,"angle":-6.39},{"time":0.1333,"angle":14.84},{"time":0.2333,"angle":0}],"translate":[{"time":0,"x":0,"y":0},{"time":0.0666,"x":-1.78,"y":-0.01},{"time":0.1,"x":-0.29,"y":0},{"time":0.1333,"x":0.37,"y":0},{"time":0.2333,"x":0,"y":0}],"scale":[{"time":0,"x":1,"y":1,"curve":"stepped"},{"time":0.2333,"x":1,"y":1}]},"bone3":{"rotate":[{"time":0,"angle":0},{"time":0.0666,"angle":4.44},{"time":0.1333,"angle":-16.16},{"time":0.2333,"angle":0}],"translate":[{"time":0,"x":0,"y":0},{"time":0.0666,"x":-1.78,"y":-0.01},{"time":0.1,"x":-0.29,"y":0},{"time":0.1333,"x":0.37,"y":0},{"time":0.2333,"x":0,"y":0}],"scale":[{"time":0,"x":1,"y":1,"curve":"stepped"},{"time":0.2333,"x":1,"y":1}]},"bone4":{"rotate":[{"time":0,"angle":0,"curve":"stepped"},{"time":0.2333,"angle":0}],"translate":[{"time":0,"x":0,"y":0,"curve":"stepped"},{"time":0.0333,"x":0,"y":0},{"time":0.0666,"x":-3.83,"y":-0.03},{"time":0.1,"x":-4.38,"y":-0.03},{"time":0.1333,"x":7.1,"y":0.07},{"time":0.1666,"x":6.62,"y":0.06},{"time":0.2333,"x":0,"y":0}],"scale":[{"time":0,"x":1,"y":1,"curve":"stepped"},{"time":0.2333,"x":1,"y":1}]}}}}}